special_agents/Agent.py
special_agents/__init__.py
special_agents/config.py
special_agents/utils.py
special_agents/agents/ContentCreator.py
special_agents/agents/FullStackDeveloper.py
special_agents/agents/ProductManager.py
special_agents/agents/__init__.py
special_agents-1.0.9.dist-info/LICENSE
special_agents-1.0.9.dist-info/METADATA
special_agents-1.0.9.dist-info/WHEEL
special_agents-1.0.9.dist-info/top_level.txt
special_agents-1.0.9.dist-info/RECORD
