Metadata-Version: 2.1
Name: special-agents
Version: 1.0.9
Summary: An Open-source Library for pre-defined LLM powered specialized agents
Home-page: https://github.com/IhabTag/special-agents
Author: Ihab Tag
Author-email: contact@ihabtag.com
License: MIT license
Classifier: Programming Language :: Python :: 3
Classifier: License :: OSI Approved :: MIT License
Classifier: Operating System :: OS Independent
Requires-Python: >=3.6
License-File: LICENSE
Requires-Dist: openai==1.25.2
